{
    "AA120": "150",
    "AAInitial": "28",
    "AAKai": "0",
    "AAKai120": "0",
    "AAMax": "130",
    "ASW120": "192",
    "ASWInitial": "47",
    "ASWKai": "0",
    "ASWKai120": "0",
    "ASWMax": "173",
    "Acc120": "175",
    "AccInitial": "64",
    "AccKai": "0",
    "AccKai120": "0",
    "AccMax": "167",
    "Air120": "0",
    "AirInitial": "0",
    "AirKai": "0",
    "AirKai120": "0",
    "AirMax": "0",
    "Ammo120": "0",
    "AmmoInitial": "0",
    "AmmoKai": "0",
    "AmmoKai120": "0",
    "AmmoMax": "0",
    "Armor": "Light",
    "ArmorKai": "Light",
    "Artist": "\u6797\u5927B",
    "ArtistLink": "[https://weibo.com/312444618 \u6797\u5927B]",
    "ArtistPixiv": "[https://www.pixiv.net/member.php?id=1245646 \u6797\u5927B]",
    "ArtistTwitter": "[https://twitter.com/lin_da_Bi \u6797\u5927B]",
    "CNName": "\u5c0f\u730e\u5154\u72ac",
    "Class": "A and B",
    "ConstructTime": "00:20:00",
    "Consumption120": "7",
    "ConsumptionInitial": "1",
    "ConsumptionKai": "0",
    "ConsumptionKai120": "0",
    "ConsumptionMax": "7",
    "Eq1BaseKai": "0",
    "Eq1BaseMax": "1",
    "Eq1EffInit": "100%",
    "Eq1EffInitKai": "",
    "Eq1EffInitMax": "120%",
    "Eq1Type": "DD Main Guns",
    "Eq2BaseKai": "0",
    "Eq2BaseMax": "2",
    "Eq2EffInit": "130%",
    "Eq2EffInitKai": "",
    "Eq2EffInitMax": "135%",
    "Eq2Type": "Torpedoes",
    "Eq3BaseKai": "0",
    "Eq3BaseMax": "1",
    "Eq3EffInit": "100%",
    "Eq3EffInitKai": "",
    "Eq3EffInitMax": "105%",
    "Eq3Type": "Anti-Air Guns",
    "Evade120": "209",
    "EvadeInitial": "78",
    "EvadeKai": "0",
    "EvadeKai120": "0",
    "EvadeMax": "203",
    "Fire120": "65",
    "FireInitial": "12",
    "FireKai": "0",
    "FireKai120": "0",
    "FireMax": "57",
    "Health120": "1349",
    "HealthInitial": "218",
    "HealthKai": "0",
    "HealthKai120": "0",
    "HealthMax": "1124",
    "JPName": "\u30d3\u30fc\u30b0\u30eb",
    "KRName": "\ube44\uae00",
    "Luck": "71",
    "Name": "Beagle",
    "Nationality": "Royal Navy",
    "Oxygen120": "0",
    "OxygenInitial": "0",
    "OxygenKai": "0",
    "OxygenKai120": "0",
    "OxygenMax": "0",
    "Rarity": "Normal",
    "Reload120": "190",
    "ReloadInitial": "70",
    "ReloadKai": "0",
    "ReloadKai120": "0",
    "ReloadMax": "165",
    "Remodel": "f",
    "RemodelId": "",
    "ShipGroup": "Standard",
    "ShipID": "086",
    "Speed": "42",
    "SpeedKai": "0",
    "SubtypeRetro": "",
    "Torp120": "354",
    "TorpInitial": "67",
    "TorpKai": "0",
    "TorpKai120": "0",
    "TorpMax": "315",
    "Type": "Destroyer",
    "VA": "[[:wikipedia:Eri_Suzuki|Eri Suzuki]]"
}