{
    "AA120": "141",
    "AAInitial": "26",
    "AAKai": "0",
    "AAKai120": "0",
    "AAMax": "123",
    "ASW120": "208",
    "ASWInitial": "51",
    "ASWKai": "0",
    "ASWKai120": "0",
    "ASWMax": "204",
    "Acc120": "183",
    "AccInitial": "67",
    "AccKai": "0",
    "AccKai120": "0",
    "AccMax": "174",
    "Air120": "0",
    "AirInitial": "0",
    "AirKai": "0",
    "AirKai120": "0",
    "AirMax": "0",
    "Ammo120": "0",
    "AmmoInitial": "0",
    "AmmoKai": "0",
    "AmmoKai120": "0",
    "AmmoMax": "0",
    "Armor": "Light",
    "ArmorKai": "Light",
    "Artist": "\u548c\u8336",
    "ArtistLink": "[https://weibo.com/538001251 \u548c\u8336_]",
    "ArtistPixiv": "[https://www.pixiv.net/member.php?id=3312169 \u548c\u8336]",
    "ArtistTwitter": "[https://twitter.com/hecha01964237 hecha]",
    "CNName": "\u5854\u5c14\u56fe",
    "Class": "Vauquelin",
    "ConstructTime": "00:26:00",
    "Consumption120": "9",
    "ConsumptionInitial": "2",
    "ConsumptionKai": "0",
    "ConsumptionKai120": "0",
    "ConsumptionMax": "9",
    "Eq1BaseMax": "1",
    "Eq1EffInit": "120%",
    "Eq1EffInitMax": "140%",
    "Eq1Type": "DD Guns",
    "Eq2BaseMax": "2",
    "Eq2EffInit": "135%",
    "Eq2EffInitMax": "140%",
    "Eq2Type": "Torpedoes",
    "Eq3BaseMax": "1",
    "Eq3EffInit": "70%",
    "Eq3EffInitMax": "75%",
    "Eq3Type": "Anti-Air Guns",
    "Evade120": "212",
    "EvadeInitial": "78",
    "EvadeKai": "0",
    "EvadeKai120": "0",
    "EvadeMax": "204",
    "Fire120": "120",
    "FireInitial": "22",
    "FireKai": "0",
    "FireKai120": "0",
    "FireMax": "104",
    "Health120": "1868",
    "HealthInitial": "301",
    "HealthKai": "0",
    "HealthKai120": "0",
    "HealthMax": "1469",
    "JPName": "\u30bf\u30eb\u30c6\u30e5",
    "Luck": "45",
    "Name": "Tartu",
    "Nationality": "Vichya Dominion",
    "Oxygen120": "0",
    "OxygenInitial": "0",
    "OxygenKai": "0",
    "OxygenKai120": "0",
    "OxygenMax": "0",
    "Rarity": "Elite",
    "Reload120": "204",
    "ReloadInitial": "75",
    "ReloadKai": "0",
    "ReloadKai120": "0",
    "ReloadMax": "177",
    "Remodel": "f",
    "ShipGroup": "Standard",
    "ShipID": "452",
    "Speed": "43",
    "SpeedKai": "0",
    "Torp120": "273",
    "TorpInitial": "51",
    "TorpKai": "0",
    "TorpKai120": "0",
    "TorpMax": "239",
    "Type": "Destroyer",
    "VA": "[https://www.imdb.com/name/nm9806307/ Eri Yukimura]"
}