{
    "AA120": "178",
    "AAInitial": "33",
    "AAKai": "0",
    "AAKai120": "0",
    "AAMax": "155",
    "ASW120": "200",
    "ASWInitial": "49",
    "ASWKai": "0",
    "ASWKai120": "0",
    "ASWMax": "180",
    "Acc120": "186",
    "AccInitial": "68",
    "AccKai": "0",
    "AccKai120": "0",
    "AccMax": "177",
    "Air120": "0",
    "AirInitial": "0",
    "AirKai": "0",
    "AirKai120": "0",
    "AirMax": "0",
    "Ammo120": "0",
    "AmmoInitial": "0",
    "AmmoKai": "0",
    "AmmoKai120": "0",
    "AmmoMax": "0",
    "Armor": "Light",
    "ArmorKai": "Light",
    "Artist": "\u5c0f\u539f\u30c8\u30e1\u592a",
    "ArtistLink": "[http://qp.banbi.net/ QP Flapper Web site]",
    "ArtistPixiv": "",
    "ArtistTwitter": "[https://twitter.com/tometa_QP \u5c0f\u539f\u30c8\u30e1\u592a QP:flapper]",
    "CNName": "Z36",
    "Class": "Type 1936B",
    "ConstructTime": "00:35:00",
    "Consumption120": "9",
    "ConsumptionInitial": "2",
    "ConsumptionKai": "0",
    "ConsumptionKai120": "0",
    "ConsumptionMax": "9",
    "Eq1EffInit": "130%",
    "Eq1EffInitKai": "",
    "Eq1EffInitMax": "145%",
    "Eq1Type": "DD Main Guns",
    "Eq2EffInit": "120%",
    "Eq2EffInitKai": "",
    "Eq2EffInitMax": "125%",
    "Eq2Type": "Torpedoes",
    "Eq3EffInit": "115%",
    "Eq3EffInitKai": "",
    "Eq3EffInitMax": "125%",
    "Eq3Type": "Anti-Air Guns",
    "Evade120": "159",
    "EvadeInitial": "59",
    "EvadeKai": "0",
    "EvadeKai120": "0",
    "EvadeMax": "153",
    "Fire120": "82",
    "FireInitial": "15",
    "FireKai": "0",
    "FireKai120": "0",
    "FireMax": "72",
    "Health120": "2092",
    "HealthInitial": "340",
    "HealthKai": "0",
    "HealthKai120": "0",
    "HealthMax": "1758",
    "Image": "Z36.png",
    "ImageBanner": "Z36Banner.png",
    "ImageBannerKai": "",
    "ImageChibi": "Z36Chibi.png",
    "ImageChibiKai": "",
    "ImageIcon": "Z36Icon.png",
    "ImageIconKai": "",
    "ImageKai": "",
    "ImageShipyardIcon": "Z36ShipyardIcon.png",
    "ImageShipyardIconKai": "",
    "JPName": "Z36",
    "KRName": "Z36",
    "LB1": "Gains Special Barrage I / Anti-Air Efficiency +5%",
    "LB2": "Max Torpedo Capacity +1 / Pre-Loaded Torpedo +1 / Main Gun Efficiency +10%",
    "LB3": "Upgrades Full Barrage I\u2192II / All Weapon Efficiency +5%",
    "Luck": "36",
    "Name": "Z36",
    "Nationality": "Iron Blood",
    "Oxygen120": "0",
    "OxygenInitial": "0",
    "OxygenKai": "0",
    "OxygenKai120": "0",
    "OxygenMax": "0",
    "Rarity": "Elite",
    "Reload120": "209",
    "ReloadInitial": "77",
    "ReloadKai": "0",
    "ReloadKai120": "0",
    "ReloadMax": "182",
    "Remodel": "f",
    "RemodelId": "",
    "ShipGroup": "Standard",
    "ShipID": "388",
    "Speed": "43",
    "SpeedKai": "0",
    "SubtypeRetro": "",
    "Torp120": "437",
    "TorpInitial": "84",
    "TorpKai": "0",
    "TorpKai120": "0",
    "TorpMax": "395",
    "Type": "Destroyer",
    "VA": "[[wikipedia:Sayuri Hara|Sayuri Hara]]",
    "Voiced": ""
}