{
    "AA120": "479",
    "AAInitial": "93",
    "AAKai": "0",
    "AAKai120": "0",
    "AAMax": "436",
    "ASW120": "203",
    "ASWInitial": "50",
    "ASWKai": "0",
    "ASWKai120": "0",
    "ASWMax": "183",
    "Acc120": "168",
    "AccInitial": "58",
    "AccKai": "0",
    "AccKai120": "0",
    "AccMax": "150",
    "Air120": "0",
    "AirInitial": "0",
    "AirKai": "0",
    "AirKai120": "0",
    "AirMax": "0",
    "Ammo120": "0",
    "AmmoInitial": "0",
    "AmmoKai": "0",
    "AmmoKai120": "0",
    "AmmoMax": "0",
    "Armor": "Light",
    "ArmorKai": "Light",
    "Artist": "Pandea",
    "ArtistLink": "[https://www.weibo.com/612325127 WongPanda_Mr]",
    "ArtistPixiv": "[https://www.pixiv.net/en/users/619064 PandeaWork]",
    "ArtistTwitter": "[https://twitter.com/Pandea_work Jimmy Pan]",
    "CNName": "\u91cc\u8bfa",
    "Class": "Atlanta",
    "ConstructTime": "01:10:00",
    "Consumption120": "11",
    "ConsumptionInitial": "3",
    "ConsumptionKai": "0",
    "ConsumptionKai120": "0",
    "ConsumptionMax": "11",
    "Eq1EffInit": "120%",
    "Eq1EffInitKai": "",
    "Eq1EffInitMax": "125%",
    "Eq1Type": "DD/CL Main Guns",
    "Eq2EffInit": "130%",
    "Eq2EffInitKai": "",
    "Eq2EffInitMax": "135%",
    "Eq2Type": "Torpedoes",
    "Eq3EffInit": "150%",
    "Eq3EffInitKai": "",
    "Eq3EffInitMax": "170%",
    "Eq3Type": "Anti-Air Guns",
    "Evade120": "95",
    "EvadeInitial": "28",
    "EvadeKai": "0",
    "EvadeKai120": "0",
    "EvadeMax": "73",
    "Fire120": "148",
    "FireInitial": "27",
    "FireKai": "0",
    "FireKai120": "0",
    "FireMax": "129",
    "Health120": "3755",
    "HealthInitial": "646",
    "HealthKai": "0",
    "HealthKai120": "0",
    "HealthMax": "3338",
    "Image": "Reno.png",
    "ImageBanner": "RenoBanner.png",
    "ImageBannerKai": "",
    "ImageChibi": "RenoChibi.png",
    "ImageChibiKai": "",
    "ImageIcon": "RenoIcon.png",
    "ImageIconKai": "",
    "ImageKai": "",
    "ImageShipyardIcon": "RenoShipyardIcon.png",
    "ImageShipyardIconKai": "",
    "JPName": "\u30ea\u30ce",
    "KRName": "",
    "LB1": "Unlock EX Barrage \u2160/AA gun efficiency +5%",
    "LB2": "Torpedo base +1/Torpedo preload +1/AA gun efficiency +10%",
    "LB3": "Improve EX Barrage/All weapons' efficiency +5%",
    "Luck": "52",
    "Name": "Reno",
    "Nationality": "Eagle Union",
    "Oxygen120": "0",
    "OxygenInitial": "0",
    "OxygenKai": "0",
    "OxygenKai120": "0",
    "OxygenMax": "0",
    "Rarity": "Super Rare",
    "Reload120": "190",
    "ReloadInitial": "70",
    "ReloadKai": "0",
    "ReloadKai120": "0",
    "ReloadMax": "165",
    "Remodel": "f",
    "RemodelId": "",
    "ShipGroup": "Standard",
    "ShipID": "445",
    "Speed": "32",
    "SpeedKai": "0",
    "SubtypeRetro": "",
    "Torp120": "196",
    "TorpInitial": "36",
    "TorpKai": "0",
    "TorpKai120": "0",
    "TorpMax": "171",
    "Type": "Light Cruiser",
    "VA": "Meiko Kawasaki",
    "Voiced": ""
}