{
    "ships": [
        {
            "Name": "HDN Neptune",
            "ShipID": "Collab001",
            "dataJSON": "ships/by-id/Collab001/ship.json"
        },
        {
            "Name": "Noire",
            "ShipID": "Collab002",
            "dataJSON": "ships/by-id/Collab002/ship.json"
        },
        {
            "Name": "Blanc",
            "ShipID": "Collab003",
            "dataJSON": "ships/by-id/Collab003/ship.json"
        },
        {
            "Name": "Vert",
            "ShipID": "Collab004",
            "dataJSON": "ships/by-id/Collab004/ship.json"
        },
        {
            "Name": "Purple Heart",
            "ShipID": "Collab005",
            "dataJSON": "ships/by-id/Collab005/ship.json"
        },
        {
            "Name": "Black Heart",
            "ShipID": "Collab006",
            "dataJSON": "ships/by-id/Collab006/ship.json"
        },
        {
            "Name": "White Heart",
            "ShipID": "Collab007",
            "dataJSON": "ships/by-id/Collab007/ship.json"
        },
        {
            "Name": "Green Heart",
            "ShipID": "Collab008",
            "dataJSON": "ships/by-id/Collab008/ship.json"
        },
        {
            "Name": "22",
            "ShipID": "Collab021",
            "dataJSON": "ships/by-id/Collab021/ship.json"
        },
        {
            "Name": "33",
            "ShipID": "Collab022",
            "dataJSON": "ships/by-id/Collab022/ship.json"
        },
        {
            "Name": "Kuon",
            "ShipID": "Collab031",
            "dataJSON": "ships/by-id/Collab031/ship.json"
        },
        {
            "Name": "Nekone",
            "ShipID": "Collab032",
            "dataJSON": "ships/by-id/Collab032/ship.json"
        },
        {
            "Name": "Rurutie",
            "ShipID": "Collab033",
            "dataJSON": "ships/by-id/Collab033/ship.json"
        },
        {
            "Name": "Uruuru",
            "ShipID": "Collab034",
            "dataJSON": "ships/by-id/Collab034/ship.json"
        },
        {
            "Name": "Saraana",
            "ShipID": "Collab035",
            "dataJSON": "ships/by-id/Collab035/ship.json"
        },
        {
            "Name": "Fumiruiru",
            "ShipID": "Collab036",
            "dataJSON": "ships/by-id/Collab036/ship.json"
        },
        {
            "Name": "Kizuna AI",
            "ShipID": "Collab041",
            "dataJSON": "ships/by-id/Collab041/ship.json"
        },
        {
            "Name": "Elegant Kizuna AI",
            "ShipID": "Collab042",
            "dataJSON": "ships/by-id/Collab042/ship.json"
        },
        {
            "Name": "Anniversary Kizuna AI",
            "ShipID": "Collab043",
            "dataJSON": "ships/by-id/Collab043/ship.json"
        },
        {
            "Name": "Super Gamer Kizuna AI",
            "ShipID": "Collab044",
            "dataJSON": "ships/by-id/Collab044/ship.json"
        },
        {
            "Name": "Shirakami Fubuki",
            "ShipID": "Collab051",
            "dataJSON": "ships/by-id/Collab051/ship.json"
        },
        {
            "Name": "Tokino Sora",
            "ShipID": "Collab052",
            "dataJSON": "ships/by-id/Collab052/ship.json"
        },
        {
            "Name": "Minato Aqua",
            "ShipID": "Collab053",
            "dataJSON": "ships/by-id/Collab053/ship.json"
        },
        {
            "Name": "Natsuiro Matsuri",
            "ShipID": "Collab054",
            "dataJSON": "ships/by-id/Collab054/ship.json"
        },
        {
            "Name": "Nakiri Ayame",
            "ShipID": "Collab055",
            "dataJSON": "ships/by-id/Collab055/ship.json"
        },
        {
            "Name": "Murasaki Shion",
            "ShipID": "Collab056",
            "dataJSON": "ships/by-id/Collab056/ship.json"
        },
        {
            "Name": "Ookami Mio",
            "ShipID": "Collab057",
            "dataJSON": "ships/by-id/Collab057/ship.json"
        },
        {
            "Name": "HMS Neptune",
            "ShipID": "Plan001",
            "dataJSON": "ships/by-id/Plan001/ship.json"
        },
        {
            "Name": "Monarch",
            "ShipID": "Plan002",
            "dataJSON": "ships/by-id/Plan002/ship.json"
        },
        {
            "Name": "Ibuki",
            "ShipID": "Plan003",
            "dataJSON": "ships/by-id/Plan003/ship.json"
        },
        {
            "Name": "Izumo",
            "ShipID": "Plan004",
            "dataJSON": "ships/by-id/Plan004/ship.json"
        },
        {
            "Name": "Roon",
            "ShipID": "Plan005",
            "dataJSON": "ships/by-id/Plan005/ship.json"
        },
        {
            "Name": "Saint Louis",
            "ShipID": "Plan006",
            "dataJSON": "ships/by-id/Plan006/ship.json"
        },
        {
            "Name": "Seattle",
            "ShipID": "Plan007",
            "dataJSON": "ships/by-id/Plan007/ship.json"
        },
        {
            "Name": "Georgia",
            "ShipID": "Plan008",
            "dataJSON": "ships/by-id/Plan008/ship.json"
        },
        {
            "Name": "Kitakaze",
            "ShipID": "Plan009",
            "dataJSON": "ships/by-id/Plan009/ship.json"
        },
        {
            "Name": "Azuma",
            "ShipID": "Plan010",
            "dataJSON": "ships/by-id/Plan010/ship.json"
        },
        {
            "Name": "Friedrich der Grosse",
            "ShipID": "Plan011",
            "dataJSON": "ships/by-id/Plan011/ship.json"
        },
        {
            "Name": "Gascogne",
            "ShipID": "Plan012",
            "dataJSON": "ships/by-id/Plan012/ship.json"
        },
        {
            "Name": "Universal Bulin",
            "ShipID": "001",
            "dataJSON": "ships/by-id/001/ship.json"
        },
        {
            "Name": "Prototype Bulin MKII",
            "ShipID": "002",
            "dataJSON": "ships/by-id/002/ship.json"
        },
        {
            "Name": "Dewey",
            "ShipID": "004",
            "dataJSON": "ships/by-id/004/ship.json"
        },
        {
            "Name": "Cassin",
            "ShipID": "005",
            "dataJSON": "ships/by-id/005/ship.json"
        },
        {
            "Name": "Downes",
            "ShipID": "006",
            "dataJSON": "ships/by-id/006/ship.json"
        },
        {
            "Name": "Gridley",
            "ShipID": "007",
            "dataJSON": "ships/by-id/007/ship.json"
        },
        {
            "Name": "Craven",
            "ShipID": "008",
            "dataJSON": "ships/by-id/008/ship.json"
        },
        {
            "Name": "McCall",
            "ShipID": "009",
            "dataJSON": "ships/by-id/009/ship.json"
        },
        {
            "Name": "Maury",
            "ShipID": "010",
            "dataJSON": "ships/by-id/010/ship.json"
        },
        {
            "Name": "Fletcher",
            "ShipID": "011",
            "dataJSON": "ships/by-id/011/ship.json"
        },
        {
            "Name": "Charles Ausburne",
            "ShipID": "013",
            "dataJSON": "ships/by-id/013/ship.json"
        },
        {
            "Name": "Thatcher",
            "ShipID": "014",
            "dataJSON": "ships/by-id/014/ship.json"
        },
        {
            "Name": "Aulick",
            "ShipID": "015",
            "dataJSON": "ships/by-id/015/ship.json"
        },
        {
            "Name": "Foote",
            "ShipID": "016",
            "dataJSON": "ships/by-id/016/ship.json"
        },
        {
            "Name": "Spence",
            "ShipID": "017",
            "dataJSON": "ships/by-id/017/ship.json"
        },
        {
            "Name": "Benson",
            "ShipID": "018",
            "dataJSON": "ships/by-id/018/ship.json"
        },
        {
            "Name": "Laffey",
            "ShipID": "019",
            "dataJSON": "ships/by-id/019/ship.json"
        },
        {
            "Name": "Sims",
            "ShipID": "026",
            "dataJSON": "ships/by-id/026/ship.json"
        },
        {
            "Name": "Hammann",
            "ShipID": "027",
            "dataJSON": "ships/by-id/027/ship.json"
        },
        {
            "Name": "Eldridge",
            "ShipID": "028",
            "dataJSON": "ships/by-id/028/ship.json"
        },
        {
            "Name": "Omaha",
            "ShipID": "029",
            "dataJSON": "ships/by-id/029/ship.json"
        },
        {
            "Name": "Raleigh",
            "ShipID": "030",
            "dataJSON": "ships/by-id/030/ship.json"
        },
        {
            "Name": "Brooklyn",
            "ShipID": "031",
            "dataJSON": "ships/by-id/031/ship.json"
        },
        {
            "Name": "Phoenix",
            "ShipID": "032",
            "dataJSON": "ships/by-id/032/ship.json"
        },
        {
            "Name": "Helena",
            "ShipID": "033",
            "dataJSON": "ships/by-id/033/ship.json"
        },
        {
            "Name": "Atlanta",
            "ShipID": "034",
            "dataJSON": "ships/by-id/034/ship.json"
        },
        {
            "Name": "Juneau",
            "ShipID": "035",
            "dataJSON": "ships/by-id/035/ship.json"
        },
        {
            "Name": "San Diego",
            "ShipID": "036",
            "dataJSON": "ships/by-id/036/ship.json"
        },
        {
            "Name": "Cleveland",
            "ShipID": "037",
            "dataJSON": "ships/by-id/037/ship.json"
        },
        {
            "Name": "Columbia",
            "ShipID": "038",
            "dataJSON": "ships/by-id/038/ship.json"
        },
        {
            "Name": "Pensacola",
            "ShipID": "039",
            "dataJSON": "ships/by-id/039/ship.json"
        },
        {
            "Name": "Salt Lake City",
            "ShipID": "040",
            "dataJSON": "ships/by-id/040/ship.json"
        },
        {
            "Name": "Northampton",
            "ShipID": "041",
            "dataJSON": "ships/by-id/041/ship.json"
        },
        {
            "Name": "Chicago",
            "ShipID": "042",
            "dataJSON": "ships/by-id/042/ship.json"
        },
        {
            "Name": "Houston",
            "ShipID": "043",
            "dataJSON": "ships/by-id/043/ship.json"
        },
        {
            "Name": "Portland",
            "ShipID": "044",
            "dataJSON": "ships/by-id/044/ship.json"
        },
        {
            "Name": "Indianapolis",
            "ShipID": "045",
            "dataJSON": "ships/by-id/045/ship.json"
        },
        {
            "Name": "Astoria",
            "ShipID": "046",
            "dataJSON": "ships/by-id/046/ship.json"
        },
        {
            "Name": "Quincy",
            "ShipID": "047",
            "dataJSON": "ships/by-id/047/ship.json"
        },
        {
            "Name": "Vincennes",
            "ShipID": "048",
            "dataJSON": "ships/by-id/048/ship.json"
        },
        {
            "Name": "Wichita",
            "ShipID": "049",
            "dataJSON": "ships/by-id/049/ship.json"
        },
        {
            "Name": "Baltimore",
            "ShipID": "050",
            "dataJSON": "ships/by-id/050/ship.json"
        },
        {
            "Name": "Nevada",
            "ShipID": "052",
            "dataJSON": "ships/by-id/052/ship.json"
        },
        {
            "Name": "Oklahoma",
            "ShipID": "053",
            "dataJSON": "ships/by-id/053/ship.json"
        },
        {
            "Name": "Pennsylvania",
            "ShipID": "054",
            "dataJSON": "ships/by-id/054/ship.json"
        },
        {
            "Name": "Arizona",
            "ShipID": "055",
            "dataJSON": "ships/by-id/055/ship.json"
        },
        {
            "Name": "Tennessee",
            "ShipID": "058",
            "dataJSON": "ships/by-id/058/ship.json"
        },
        {
            "Name": "California",
            "ShipID": "059",
            "dataJSON": "ships/by-id/059/ship.json"
        },
        {
            "Name": "Colorado",
            "ShipID": "060",
            "dataJSON": "ships/by-id/060/ship.json"
        },
        {
            "Name": "Maryland",
            "ShipID": "061",
            "dataJSON": "ships/by-id/061/ship.json"
        },
        {
            "Name": "West Virginia",
            "ShipID": "062",
            "dataJSON": "ships/by-id/062/ship.json"
        },
        {
            "Name": "North Carolina",
            "ShipID": "063",
            "dataJSON": "ships/by-id/063/ship.json"
        },
        {
            "Name": "Washington",
            "ShipID": "064",
            "dataJSON": "ships/by-id/064/ship.json"
        },
        {
            "Name": "South Dakota",
            "ShipID": "065",
            "dataJSON": "ships/by-id/065/ship.json"
        },
        {
            "Name": "Long Island",
            "ShipID": "070",
            "dataJSON": "ships/by-id/070/ship.json"
        },
        {
            "Name": "Bogue",
            "ShipID": "071",
            "dataJSON": "ships/by-id/071/ship.json"
        },
        {
            "Name": "Langley",
            "ShipID": "072",
            "dataJSON": "ships/by-id/072/ship.json"
        },
        {
            "Name": "Lexington",
            "ShipID": "073",
            "dataJSON": "ships/by-id/073/ship.json"
        },
        {
            "Name": "Saratoga",
            "ShipID": "074",
            "dataJSON": "ships/by-id/074/ship.json"
        },
        {
            "Name": "Ranger",
            "ShipID": "075",
            "dataJSON": "ships/by-id/075/ship.json"
        },
        {
            "Name": "Yorktown",
            "ShipID": "076",
            "dataJSON": "ships/by-id/076/ship.json"
        },
        {
            "Name": "Enterprise",
            "ShipID": "077",
            "dataJSON": "ships/by-id/077/ship.json"
        },
        {
            "Name": "Hornet",
            "ShipID": "078",
            "dataJSON": "ships/by-id/078/ship.json"
        },
        {
            "Name": "Wasp",
            "ShipID": "079",
            "dataJSON": "ships/by-id/079/ship.json"
        },
        {
            "Name": "Vestal",
            "ShipID": "080",
            "dataJSON": "ships/by-id/080/ship.json"
        },
        {
            "Name": "Amazon",
            "ShipID": "081",
            "dataJSON": "ships/by-id/081/ship.json"
        },
        {
            "Name": "Acasta",
            "ShipID": "082",
            "dataJSON": "ships/by-id/082/ship.json"
        },
        {
            "Name": "Ardent",
            "ShipID": "083",
            "dataJSON": "ships/by-id/083/ship.json"
        },
        {
            "Name": "Beagle",
            "ShipID": "086",
            "dataJSON": "ships/by-id/086/ship.json"
        },
        {
            "Name": "Bulldog",
            "ShipID": "087",
            "dataJSON": "ships/by-id/087/ship.json"
        },
        {
            "Name": "Comet",
            "ShipID": "088",
            "dataJSON": "ships/by-id/088/ship.json"
        },
        {
            "Name": "Crescent",
            "ShipID": "089",
            "dataJSON": "ships/by-id/089/ship.json"
        },
        {
            "Name": "Cygnet",
            "ShipID": "090",
            "dataJSON": "ships/by-id/090/ship.json"
        },
        {
            "Name": "Foxhound",
            "ShipID": "091",
            "dataJSON": "ships/by-id/091/ship.json"
        },
        {
            "Name": "Fortune",
            "ShipID": "092",
            "dataJSON": "ships/by-id/092/ship.json"
        },
        {
            "Name": "Grenville",
            "ShipID": "093",
            "dataJSON": "ships/by-id/093/ship.json"
        },
        {
            "Name": "Glowworm",
            "ShipID": "094",
            "dataJSON": "ships/by-id/094/ship.json"
        },
        {
            "Name": "Hardy",
            "ShipID": "096",
            "dataJSON": "ships/by-id/096/ship.json"
        },
        {
            "Name": "Hunter",
            "ShipID": "100",
            "dataJSON": "ships/by-id/100/ship.json"
        },
        {
            "Name": "Javelin",
            "ShipID": "101",
            "dataJSON": "ships/by-id/101/ship.json"
        },
        {
            "Name": "Juno",
            "ShipID": "102",
            "dataJSON": "ships/by-id/102/ship.json"
        },
        {
            "Name": "Vampire",
            "ShipID": "103",
            "dataJSON": "ships/by-id/103/ship.json"
        },
        {
            "Name": "Leander",
            "ShipID": "104",
            "dataJSON": "ships/by-id/104/ship.json"
        },
        {
            "Name": "Achilles",
            "ShipID": "105",
            "dataJSON": "ships/by-id/105/ship.json"
        },
        {
            "Name": "Ajax",
            "ShipID": "106",
            "dataJSON": "ships/by-id/106/ship.json"
        },
        {
            "Name": "Dido",
            "ShipID": "107",
            "dataJSON": "ships/by-id/107/ship.json"
        },
        {
            "Name": "Southampton",
            "ShipID": "110",
            "dataJSON": "ships/by-id/110/ship.json"
        },
        {
            "Name": "Sheffield",
            "ShipID": "111",
            "dataJSON": "ships/by-id/111/ship.json"
        },
        {
            "Name": "Gloucester",
            "ShipID": "113",
            "dataJSON": "ships/by-id/113/ship.json"
        },
        {
            "Name": "Edinburgh",
            "ShipID": "114",
            "dataJSON": "ships/by-id/114/ship.json"
        },
        {
            "Name": "Belfast",
            "ShipID": "115",
            "dataJSON": "ships/by-id/115/ship.json"
        },
        {
            "Name": "Arethusa",
            "ShipID": "116",
            "dataJSON": "ships/by-id/116/ship.json"
        },
        {
            "Name": "Galatea",
            "ShipID": "117",
            "dataJSON": "ships/by-id/117/ship.json"
        },
        {
            "Name": "Aurora",
            "ShipID": "118",
            "dataJSON": "ships/by-id/118/ship.json"
        },
        {
            "Name": "London",
            "ShipID": "119",
            "dataJSON": "ships/by-id/119/ship.json"
        },
        {
            "Name": "Shropshire",
            "ShipID": "120",
            "dataJSON": "ships/by-id/120/ship.json"
        },
        {
            "Name": "Kent",
            "ShipID": "121",
            "dataJSON": "ships/by-id/121/ship.json"
        },
        {
            "Name": "Suffolk",
            "ShipID": "122",
            "dataJSON": "ships/by-id/122/ship.json"
        },
        {
            "Name": "Norfolk",
            "ShipID": "123",
            "dataJSON": "ships/by-id/123/ship.json"
        },
        {
            "Name": "Dorsetshire",
            "ShipID": "124",
            "dataJSON": "ships/by-id/124/ship.json"
        },
        {
            "Name": "York",
            "ShipID": "125",
            "dataJSON": "ships/by-id/125/ship.json"
        },
        {
            "Name": "Exeter",
            "ShipID": "126",
            "dataJSON": "ships/by-id/126/ship.json"
        },
        {
            "Name": "Renown",
            "ShipID": "127",
            "dataJSON": "ships/by-id/127/ship.json"
        },
        {
            "Name": "Repulse",
            "ShipID": "128",
            "dataJSON": "ships/by-id/128/ship.json"
        },
        {
            "Name": "Hood",
            "ShipID": "129",
            "dataJSON": "ships/by-id/129/ship.json"
        },
        {
            "Name": "Queen Elizabeth",
            "ShipID": "130",
            "dataJSON": "ships/by-id/130/ship.json"
        },
        {
            "Name": "Warspite",
            "ShipID": "131",
            "dataJSON": "ships/by-id/131/ship.json"
        },
        {
            "Name": "Nelson",
            "ShipID": "132",
            "dataJSON": "ships/by-id/132/ship.json"
        },
        {
            "Name": "Rodney",
            "ShipID": "133",
            "dataJSON": "ships/by-id/133/ship.json"
        },
        {
            "Name": "King George V",
            "ShipID": "134",
            "dataJSON": "ships/by-id/134/ship.json"
        },
        {
            "Name": "Prince of Wales",
            "ShipID": "135",
            "dataJSON": "ships/by-id/135/ship.json"
        },
        {
            "Name": "Duke of York",
            "ShipID": "136",
            "dataJSON": "ships/by-id/136/ship.json"
        },
        {
            "Name": "Hermes",
            "ShipID": "140",
            "dataJSON": "ships/by-id/140/ship.json"
        },
        {
            "Name": "Unicorn",
            "ShipID": "142",
            "dataJSON": "ships/by-id/142/ship.json"
        },
        {
            "Name": "Ark Royal",
            "ShipID": "144",
            "dataJSON": "ships/by-id/144/ship.json"
        },
        {
            "Name": "Illustrious",
            "ShipID": "145",
            "dataJSON": "ships/by-id/145/ship.json"
        },
        {
            "Name": "Victorious",
            "ShipID": "146",
            "dataJSON": "ships/by-id/146/ship.json"
        },
        {
            "Name": "Formidable",
            "ShipID": "147",
            "dataJSON": "ships/by-id/147/ship.json"
        },
        {
            "Name": "Glorious",
            "ShipID": "148",
            "dataJSON": "ships/by-id/148/ship.json"
        },
        {
            "Name": "Erebus",
            "ShipID": "149",
            "dataJSON": "ships/by-id/149/ship.json"
        },
        {
            "Name": "Terror",
            "ShipID": "150",
            "dataJSON": "ships/by-id/150/ship.json"
        },
        {
            "Name": "Fubuki",
            "ShipID": "151",
            "dataJSON": "ships/by-id/151/ship.json"
        },
        {
            "Name": "Ayanami",
            "ShipID": "155",
            "dataJSON": "ships/by-id/155/ship.json"
        },
        {
            "Name": "Akatsuki",
            "ShipID": "159",
            "dataJSON": "ships/by-id/159/ship.json"
        },
        {
            "Name": "Hibiki",
            "ShipID": "160",
            "dataJSON": "ships/by-id/160/ship.json"
        },
        {
            "Name": "Ikazuchi",
            "ShipID": "161",
            "dataJSON": "ships/by-id/161/ship.json"
        },
        {
            "Name": "Inazuma",
            "ShipID": "162",
            "dataJSON": "ships/by-id/162/ship.json"
        },
        {
            "Name": "Shiratsuyu",
            "ShipID": "163",
            "dataJSON": "ships/by-id/163/ship.json"
        },
        {
            "Name": "Yuudachi",
            "ShipID": "164",
            "dataJSON": "ships/by-id/164/ship.json"
        },
        {
            "Name": "Shigure",
            "ShipID": "165",
            "dataJSON": "ships/by-id/165/ship.json"
        },
        {
            "Name": "Yukikaze",
            "ShipID": "166",
            "dataJSON": "ships/by-id/166/ship.json"
        },
        {
            "Name": "Kagerou",
            "ShipID": "167",
            "dataJSON": "ships/by-id/167/ship.json"
        },
        {
            "Name": "Shiranui",
            "ShipID": "168",
            "dataJSON": "ships/by-id/168/ship.json"
        },
        {
            "Name": "Nowaki",
            "ShipID": "170",
            "dataJSON": "ships/by-id/170/ship.json"
        },
        {
            "Name": "Hatsuharu",
            "ShipID": "171",
            "dataJSON": "ships/by-id/171/ship.json"
        },
        {
            "Name": "Wakaba",
            "ShipID": "173",
            "dataJSON": "ships/by-id/173/ship.json"
        },
        {
            "Name": "Hatsushimo",
            "ShipID": "174",
            "dataJSON": "ships/by-id/174/ship.json"
        },
        {
            "Name": "Ariake",
            "ShipID": "175",
            "dataJSON": "ships/by-id/175/ship.json"
        },
        {
            "Name": "Yuugure",
            "ShipID": "176",
            "dataJSON": "ships/by-id/176/ship.json"
        },
        {
            "Name": "Kuroshio",
            "ShipID": "177",
            "dataJSON": "ships/by-id/177/ship.json"
        },
        {
            "Name": "Oyashio",
            "ShipID": "178",
            "dataJSON": "ships/by-id/178/ship.json"
        },
        {
            "Name": "Yuubari",
            "ShipID": "179",
            "dataJSON": "ships/by-id/179/ship.json"
        },
        {
            "Name": "Nagara",
            "ShipID": "182",
            "dataJSON": "ships/by-id/182/ship.json"
        },
        {
            "Name": "Isuzu",
            "ShipID": "183",
            "dataJSON": "ships/by-id/183/ship.json"
        },
        {
            "Name": "Kinu",
            "ShipID": "186",
            "dataJSON": "ships/by-id/186/ship.json"
        },
        {
            "Name": "Abukuma",
            "ShipID": "187",
            "dataJSON": "ships/by-id/187/ship.json"
        },
        {
            "Name": "Mogami",
            "ShipID": "188",
            "dataJSON": "ships/by-id/188/ship.json"
        },
        {
            "Name": "Mikuma",
            "ShipID": "189",
            "dataJSON": "ships/by-id/189/ship.json"
        },
        {
            "Name": "Furutaka",
            "ShipID": "190",
            "dataJSON": "ships/by-id/190/ship.json"
        },
        {
            "Name": "Kako",
            "ShipID": "191",
            "dataJSON": "ships/by-id/191/ship.json"
        },
        {
            "Name": "Aoba",
            "ShipID": "192",
            "dataJSON": "ships/by-id/192/ship.json"
        },
        {
            "Name": "Kinugasa",
            "ShipID": "193",
            "dataJSON": "ships/by-id/193/ship.json"
        },
        {
            "Name": "Myoukou",
            "ShipID": "196",
            "dataJSON": "ships/by-id/196/ship.json"
        },
        {
            "Name": "Nachi",
            "ShipID": "197",
            "dataJSON": "ships/by-id/197/ship.json"
        },
        {
            "Name": "Ashigara",
            "ShipID": "198",
            "dataJSON": "ships/by-id/198/ship.json"
        },
        {
            "Name": "Takao",
            "ShipID": "200",
            "dataJSON": "ships/by-id/200/ship.json"
        },
        {
            "Name": "Atago",
            "ShipID": "201",
            "dataJSON": "ships/by-id/201/ship.json"
        },
        {
            "Name": "Maya",
            "ShipID": "202",
            "dataJSON": "ships/by-id/202/ship.json"
        },
        {
            "Name": "Choukai",
            "ShipID": "203",
            "dataJSON": "ships/by-id/203/ship.json"
        },
        {
            "Name": "Kongou",
            "ShipID": "204",
            "dataJSON": "ships/by-id/204/ship.json"
        },
        {
            "Name": "Hiei",
            "ShipID": "205",
            "dataJSON": "ships/by-id/205/ship.json"
        },
        {
            "Name": "Haruna",
            "ShipID": "206",
            "dataJSON": "ships/by-id/206/ship.json"
        },
        {
            "Name": "Kirishima",
            "ShipID": "207",
            "dataJSON": "ships/by-id/207/ship.json"
        },
        {
            "Name": "Fusou",
            "ShipID": "208",
            "dataJSON": "ships/by-id/208/ship.json"
        },
        {
            "Name": "Yamashiro",
            "ShipID": "209",
            "dataJSON": "ships/by-id/209/ship.json"
        },
        {
            "Name": "Ise",
            "ShipID": "210",
            "dataJSON": "ships/by-id/210/ship.json"
        },
        {
            "Name": "Hyuuga",
            "ShipID": "211",
            "dataJSON": "ships/by-id/211/ship.json"
        },
        {
            "Name": "Nagato",
            "ShipID": "212",
            "dataJSON": "ships/by-id/212/ship.json"
        },
        {
            "Name": "Mutsu",
            "ShipID": "213",
            "dataJSON": "ships/by-id/213/ship.json"
        },
        {
            "Name": "Tosa",
            "ShipID": "215",
            "dataJSON": "ships/by-id/215/ship.json"
        },
        {
            "Name": "Hiyou",
            "ShipID": "218",
            "dataJSON": "ships/by-id/218/ship.json"
        },
        {
            "Name": "Junyou",
            "ShipID": "219",
            "dataJSON": "ships/by-id/219/ship.json"
        },
        {
            "Name": "Houshou",
            "ShipID": "220",
            "dataJSON": "ships/by-id/220/ship.json"
        },
        {
            "Name": "Shouhou",
            "ShipID": "222",
            "dataJSON": "ships/by-id/222/ship.json"
        },
        {
            "Name": "Ryuujou",
            "ShipID": "223",
            "dataJSON": "ships/by-id/223/ship.json"
        },
        {
            "Name": "Akagi",
            "ShipID": "224",
            "dataJSON": "ships/by-id/224/ship.json"
        },
        {
            "Name": "Kaga",
            "ShipID": "225",
            "dataJSON": "ships/by-id/225/ship.json"
        },
        {
            "Name": "Souryuu",
            "ShipID": "226",
            "dataJSON": "ships/by-id/226/ship.json"
        },
        {
            "Name": "Hiryuu",
            "ShipID": "227",
            "dataJSON": "ships/by-id/227/ship.json"
        },
        {
            "Name": "Shoukaku",
            "ShipID": "228",
            "dataJSON": "ships/by-id/228/ship.json"
        },
        {
            "Name": "Zuikaku",
            "ShipID": "229",
            "dataJSON": "ships/by-id/229/ship.json"
        },
        {
            "Name": "Taihou",
            "ShipID": "230",
            "dataJSON": "ships/by-id/230/ship.json"
        },
        {
            "Name": "Akashi",
            "ShipID": "232",
            "dataJSON": "ships/by-id/232/ship.json"
        },
        {
            "Name": "Z1",
            "ShipID": "233",
            "dataJSON": "ships/by-id/233/ship.json"
        },
        {
            "Name": "Z23",
            "ShipID": "236",
            "dataJSON": "ships/by-id/236/ship.json"
        },
        {
            "Name": "Z25",
            "ShipID": "237",
            "dataJSON": "ships/by-id/237/ship.json"
        },
        {
            "Name": "K\u00f6nigsberg",
            "ShipID": "238",
            "dataJSON": "ships/by-id/238/ship.json"
        },
        {
            "Name": "Karlsruhe",
            "ShipID": "239",
            "dataJSON": "ships/by-id/239/ship.json"
        },
        {
            "Name": "K\u00f6ln",
            "ShipID": "240",
            "dataJSON": "ships/by-id/240/ship.json"
        },
        {
            "Name": "Leipzig",
            "ShipID": "241",
            "dataJSON": "ships/by-id/241/ship.json"
        },
        {
            "Name": "Admiral Hipper",
            "ShipID": "242",
            "dataJSON": "ships/by-id/242/ship.json"
        },
        {
            "Name": "Prinz Eugen",
            "ShipID": "244",
            "dataJSON": "ships/by-id/244/ship.json"
        },
        {
            "Name": "Deutschland",
            "ShipID": "245",
            "dataJSON": "ships/by-id/245/ship.json"
        },
        {
            "Name": "Admiral Graf Spee",
            "ShipID": "246",
            "dataJSON": "ships/by-id/246/ship.json"
        },
        {
            "Name": "Scharnhorst",
            "ShipID": "248",
            "dataJSON": "ships/by-id/248/ship.json"
        },
        {
            "Name": "Gneisenau",
            "ShipID": "249",
            "dataJSON": "ships/by-id/249/ship.json"
        },
        {
            "Name": "Bismarck",
            "ShipID": "250",
            "dataJSON": "ships/by-id/250/ship.json"
        },
        {
            "Name": "Tirpitz",
            "ShipID": "251",
            "dataJSON": "ships/by-id/251/ship.json"
        },
        {
            "Name": "Graf Zeppelin",
            "ShipID": "252",
            "dataJSON": "ships/by-id/252/ship.json"
        },
        {
            "Name": "An Shan",
            "ShipID": "253",
            "dataJSON": "ships/by-id/253/ship.json"
        },
        {
            "Name": "Fu Shun",
            "ShipID": "254",
            "dataJSON": "ships/by-id/254/ship.json"
        },
        {
            "Name": "Chang Chun",
            "ShipID": "255",
            "dataJSON": "ships/by-id/255/ship.json"
        },
        {
            "Name": "Tai Yuan",
            "ShipID": "256",
            "dataJSON": "ships/by-id/256/ship.json"
        },
        {
            "Name": "Yat Sen",
            "ShipID": "257",
            "dataJSON": "ships/by-id/257/ship.json"
        },
        {
            "Name": "Ning Hai",
            "ShipID": "258",
            "dataJSON": "ships/by-id/258/ship.json"
        },
        {
            "Name": "Ping Hai",
            "ShipID": "259",
            "dataJSON": "ships/by-id/259/ship.json"
        },
        {
            "Name": "Avrora",
            "ShipID": "262",
            "dataJSON": "ships/by-id/262/ship.json"
        },
        {
            "Name": "Bailey",
            "ShipID": "263",
            "dataJSON": "ships/by-id/263/ship.json"
        },
        {
            "Name": "Z19",
            "ShipID": "264",
            "dataJSON": "ships/by-id/264/ship.json"
        },
        {
            "Name": "Z20",
            "ShipID": "265",
            "dataJSON": "ships/by-id/265/ship.json"
        },
        {
            "Name": "Z21",
            "ShipID": "266",
            "dataJSON": "ships/by-id/266/ship.json"
        },
        {
            "Name": "Z46",
            "ShipID": "267",
            "dataJSON": "ships/by-id/267/ship.json"
        },
        {
            "Name": "Kamikaze",
            "ShipID": "269",
            "dataJSON": "ships/by-id/269/ship.json"
        },
        {
            "Name": "Matsukaze",
            "ShipID": "270",
            "dataJSON": "ships/by-id/270/ship.json"
        },
        {
            "Name": "Mutsuki",
            "ShipID": "271",
            "dataJSON": "ships/by-id/271/ship.json"
        },
        {
            "Name": "Kisaragi",
            "ShipID": "272",
            "dataJSON": "ships/by-id/272/ship.json"
        },
        {
            "Name": "Uzuki",
            "ShipID": "274",
            "dataJSON": "ships/by-id/274/ship.json"
        },
        {
            "Name": "Minazuki",
            "ShipID": "276",
            "dataJSON": "ships/by-id/276/ship.json"
        },
        {
            "Name": "Fumizuki",
            "ShipID": "277",
            "dataJSON": "ships/by-id/277/ship.json"
        },
        {
            "Name": "Nagatsuki",
            "ShipID": "278",
            "dataJSON": "ships/by-id/278/ship.json"
        },
        {
            "Name": "Mikazuki",
            "ShipID": "280",
            "dataJSON": "ships/by-id/280/ship.json"
        },
        {
            "Name": "Kawakaze",
            "ShipID": "288",
            "dataJSON": "ships/by-id/288/ship.json"
        },
        {
            "Name": "Kiyonami",
            "ShipID": "293",
            "dataJSON": "ships/by-id/293/ship.json"
        },
        {
            "Name": "Niizuki",
            "ShipID": "295",
            "dataJSON": "ships/by-id/295/ship.json"
        },
        {
            "Name": "Harutsuki",
            "ShipID": "296",
            "dataJSON": "ships/by-id/296/ship.json"
        },
        {
            "Name": "Yoizuki",
            "ShipID": "297",
            "dataJSON": "ships/by-id/297/ship.json"
        },
        {
            "Name": "Radford",
            "ShipID": "299",
            "dataJSON": "ships/by-id/299/ship.json"
        },
        {
            "Name": "Jenkins",
            "ShipID": "300",
            "dataJSON": "ships/by-id/300/ship.json"
        },
        {
            "Name": "Nicholas",
            "ShipID": "301",
            "dataJSON": "ships/by-id/301/ship.json"
        },
        {
            "Name": "Richmond",
            "ShipID": "303",
            "dataJSON": "ships/by-id/303/ship.json"
        },
        {
            "Name": "Honolulu",
            "ShipID": "304",
            "dataJSON": "ships/by-id/304/ship.json"
        },
        {
            "Name": "St. Louis",
            "ShipID": "305",
            "dataJSON": "ships/by-id/305/ship.json"
        },
        {
            "Name": "Jupiter",
            "ShipID": "306",
            "dataJSON": "ships/by-id/306/ship.json"
        },
        {
            "Name": "Jersey",
            "ShipID": "307",
            "dataJSON": "ships/by-id/307/ship.json"
        },
        {
            "Name": "Sendai",
            "ShipID": "308",
            "dataJSON": "ships/by-id/308/ship.json"
        },
        {
            "Name": "Jintsuu",
            "ShipID": "309",
            "dataJSON": "ships/by-id/309/ship.json"
        },
        {
            "Name": "Naka",
            "ShipID": "310",
            "dataJSON": "ships/by-id/310/ship.json"
        },
        {
            "Name": "Urakaze",
            "ShipID": "316",
            "dataJSON": "ships/by-id/316/ship.json"
        },
        {
            "Name": "Isokaze",
            "ShipID": "317",
            "dataJSON": "ships/by-id/317/ship.json"
        },
        {
            "Name": "Hamakaze",
            "ShipID": "318",
            "dataJSON": "ships/by-id/318/ship.json"
        },
        {
            "Name": "Tanikaze",
            "ShipID": "319",
            "dataJSON": "ships/by-id/319/ship.json"
        },
        {
            "Name": "Mikasa",
            "ShipID": "320",
            "dataJSON": "ships/by-id/320/ship.json"
        },
        {
            "Name": "Agano",
            "ShipID": "321",
            "dataJSON": "ships/by-id/321/ship.json"
        },
        {
            "Name": "Noshiro",
            "ShipID": "322",
            "dataJSON": "ships/by-id/322/ship.json"
        },
        {
            "Name": "Matchless",
            "ShipID": "325",
            "dataJSON": "ships/by-id/325/ship.json"
        },
        {
            "Name": "Musketeer",
            "ShipID": "326",
            "dataJSON": "ships/by-id/326/ship.json"
        },
        {
            "Name": "Fiji",
            "ShipID": "327",
            "dataJSON": "ships/by-id/327/ship.json"
        },
        {
            "Name": "Jamaica",
            "ShipID": "328",
            "dataJSON": "ships/by-id/328/ship.json"
        },
        {
            "Name": "Montpelier",
            "ShipID": "329",
            "dataJSON": "ships/by-id/329/ship.json"
        },
        {
            "Name": "Denver",
            "ShipID": "330",
            "dataJSON": "ships/by-id/330/ship.json"
        },
        {
            "Name": "Asashio",
            "ShipID": "331",
            "dataJSON": "ships/by-id/331/ship.json"
        },
        {
            "Name": "Ooshio",
            "ShipID": "332",
            "dataJSON": "ships/by-id/332/ship.json"
        },
        {
            "Name": "Michishio",
            "ShipID": "333",
            "dataJSON": "ships/by-id/333/ship.json"
        },
        {
            "Name": "Arashio",
            "ShipID": "334",
            "dataJSON": "ships/by-id/334/ship.json"
        },
        {
            "Name": "Little Bel",
            "ShipID": "335",
            "dataJSON": "ships/by-id/335/ship.json"
        },
        {
            "Name": "Abercrombie",
            "ShipID": "336",
            "dataJSON": "ships/by-id/336/ship.json"
        },
        {
            "Name": "Sussex",
            "ShipID": "337",
            "dataJSON": "ships/by-id/337/ship.json"
        },
        {
            "Name": "I-19",
            "ShipID": "338",
            "dataJSON": "ships/by-id/338/ship.json"
        },
        {
            "Name": "I-26",
            "ShipID": "339",
            "dataJSON": "ships/by-id/339/ship.json"
        },
        {
            "Name": "I-58",
            "ShipID": "340",
            "dataJSON": "ships/by-id/340/ship.json"
        },
        {
            "Name": "U-81",
            "ShipID": "341",
            "dataJSON": "ships/by-id/341/ship.json"
        },
        {
            "Name": "Dace",
            "ShipID": "342",
            "dataJSON": "ships/by-id/342/ship.json"
        },
        {
            "Name": "U-47",
            "ShipID": "343",
            "dataJSON": "ships/by-id/343/ship.json"
        },
        {
            "Name": "U-557",
            "ShipID": "344",
            "dataJSON": "ships/by-id/344/ship.json"
        },
        {
            "Name": "Z35",
            "ShipID": "345",
            "dataJSON": "ships/by-id/345/ship.json"
        },
        {
            "Name": "Z18",
            "ShipID": "346",
            "dataJSON": "ships/by-id/346/ship.json"
        },
        {
            "Name": "Le Triomphant",
            "ShipID": "347",
            "dataJSON": "ships/by-id/347/ship.json"
        },
        {
            "Name": "Forbin",
            "ShipID": "348",
            "dataJSON": "ships/by-id/348/ship.json"
        },
        {
            "Name": "\u00c9mile Bertin",
            "ShipID": "349",
            "dataJSON": "ships/by-id/349/ship.json"
        },
        {
            "Name": "Surcouf",
            "ShipID": "350",
            "dataJSON": "ships/by-id/350/ship.json"
        },
        {
            "Name": "Le Mars",
            "ShipID": "351",
            "dataJSON": "ships/by-id/351/ship.json"
        },
        {
            "Name": "Dunkerque",
            "ShipID": "352",
            "dataJSON": "ships/by-id/352/ship.json"
        },
        {
            "Name": "Jean Bart",
            "ShipID": "353",
            "dataJSON": "ships/by-id/353/ship.json"
        },
        {
            "Name": "Massachusetts",
            "ShipID": "354",
            "dataJSON": "ships/by-id/354/ship.json"
        },
        {
            "Name": "Bush",
            "ShipID": "355",
            "dataJSON": "ships/by-id/355/ship.json"
        },
        {
            "Name": "Centaur",
            "ShipID": "356",
            "dataJSON": "ships/by-id/356/ship.json"
        },
        {
            "Name": "Essex",
            "ShipID": "357",
            "dataJSON": "ships/by-id/357/ship.json"
        },
        {
            "Name": "Albacore",
            "ShipID": "358",
            "dataJSON": "ships/by-id/358/ship.json"
        },
        {
            "Name": "Le T\u00e9m\u00e9raire",
            "ShipID": "359",
            "dataJSON": "ships/by-id/359/ship.json"
        },
        {
            "Name": "Memphis",
            "ShipID": "360",
            "dataJSON": "ships/by-id/360/ship.json"
        },
        {
            "Name": "Newcastle",
            "ShipID": "361",
            "dataJSON": "ships/by-id/361/ship.json"
        },
        {
            "Name": "Hobby",
            "ShipID": "362",
            "dataJSON": "ships/by-id/362/ship.json"
        },
        {
            "Name": "Kalk",
            "ShipID": "363",
            "dataJSON": "ships/by-id/363/ship.json"
        },
        {
            "Name": "Minneapolis",
            "ShipID": "364",
            "dataJSON": "ships/by-id/364/ship.json"
        },
        {
            "Name": "Hazelwood",
            "ShipID": "365",
            "dataJSON": "ships/by-id/365/ship.json"
        },
        {
            "Name": "Concord",
            "ShipID": "366",
            "dataJSON": "ships/by-id/366/ship.json"
        },
        {
            "Name": "Amagi",
            "ShipID": "367",
            "dataJSON": "ships/by-id/367/ship.json"
        },
        {
            "Name": "Kaga (Battleship)",
            "ShipID": "368",
            "dataJSON": "ships/by-id/368/ship.json"
        },
        {
            "Name": "Hatakaze",
            "ShipID": "369",
            "dataJSON": "ships/by-id/369/ship.json"
        },
        {
            "Name": "Makinami",
            "ShipID": "370",
            "dataJSON": "ships/by-id/370/ship.json"
        },
        {
            "Name": "Sirius",
            "ShipID": "371",
            "dataJSON": "ships/by-id/371/ship.json"
        },
        {
            "Name": "Curacoa",
            "ShipID": "372",
            "dataJSON": "ships/by-id/372/ship.json"
        },
        {
            "Name": "Curlew",
            "ShipID": "373",
            "dataJSON": "ships/by-id/373/ship.json"
        },
        {
            "Name": "Kimberly",
            "ShipID": "374",
            "dataJSON": "ships/by-id/374/ship.json"
        },
        {
            "Name": "Mullany",
            "ShipID": "375",
            "dataJSON": "ships/by-id/375/ship.json"
        },
        {
            "Name": "Chaser",
            "ShipID": "376",
            "dataJSON": "ships/by-id/376/ship.json"
        },
        {
            "Name": "Independence",
            "ShipID": "377",
            "dataJSON": "ships/by-id/377/ship.json"
        },
        {
            "Name": "Shangri-La",
            "ShipID": "378",
            "dataJSON": "ships/by-id/378/ship.json"
        },
        {
            "Name": "Z2",
            "ShipID": "379",
            "dataJSON": "ships/by-id/379/ship.json"
        },
        {
            "Name": "Bunker Hill",
            "ShipID": "380",
            "dataJSON": "ships/by-id/380/ship.json"
        },
        {
            "Name": "I-13",
            "ShipID": "381",
            "dataJSON": "ships/by-id/381/ship.json"
        },
        {
            "Name": "Suzuya",
            "ShipID": "382",
            "dataJSON": "ships/by-id/382/ship.json"
        },
        {
            "Name": "Hiei-chan",
            "ShipID": "383",
            "dataJSON": "ships/by-id/383/ship.json"
        },
        {
            "Name": "Akagi-chan",
            "ShipID": "384",
            "dataJSON": "ships/by-id/384/ship.json"
        },
        {
            "Name": "Zeppy",
            "ShipID": "385",
            "dataJSON": "ships/by-id/385/ship.json"
        },
        {
            "Name": "U-556",
            "ShipID": "386",
            "dataJSON": "ships/by-id/386/ship.json"
        },
        {
            "Name": "U-73",
            "ShipID": "387",
            "dataJSON": "ships/by-id/387/ship.json"
        },
        {
            "Name": "Z36",
            "ShipID": "388",
            "dataJSON": "ships/by-id/388/ship.json"
        },
        {
            "Name": "Echo",
            "ShipID": "389",
            "dataJSON": "ships/by-id/389/ship.json"
        },
        {
            "Name": "Lena",
            "ShipID": "390",
            "dataJSON": "ships/by-id/390/ship.json"
        },
        {
            "Name": "Clevelad",
            "ShipID": "391",
            "dataJSON": "ships/by-id/391/ship.json"
        },
        {
            "Name": "Li'l Sandy",
            "ShipID": "392",
            "dataJSON": "ships/by-id/392/ship.json"
        },
        {
            "Name": "Swiftsure",
            "ShipID": "393",
            "dataJSON": "ships/by-id/393/ship.json"
        },
        {
            "Name": "Le Malin",
            "ShipID": "394",
            "dataJSON": "ships/by-id/394/ship.json"
        },
        {
            "Name": "L'Opini\u00e2tre",
            "ShipID": "395",
            "dataJSON": "ships/by-id/395/ship.json"
        },
        {
            "Name": "I-25",
            "ShipID": "396",
            "dataJSON": "ships/by-id/396/ship.json"
        },
        {
            "Name": "I-56",
            "ShipID": "397",
            "dataJSON": "ships/by-id/397/ship.json"
        },
        {
            "Name": "I-168",
            "ShipID": "398",
            "dataJSON": "ships/by-id/398/ship.json"
        },
        {
            "Name": "U-101",
            "ShipID": "399",
            "dataJSON": "ships/by-id/399/ship.json"
        },
        {
            "Name": "U-522",
            "ShipID": "400",
            "dataJSON": "ships/by-id/400/ship.json"
        },
        {
            "Name": "Alabama",
            "ShipID": "401",
            "dataJSON": "ships/by-id/401/ship.json"
        },
        {
            "Name": "Cavalla",
            "ShipID": "402",
            "dataJSON": "ships/by-id/402/ship.json"
        },
        {
            "Name": "Bataan",
            "ShipID": "403",
            "dataJSON": "ships/by-id/403/ship.json"
        },
        {
            "Name": "San Juan",
            "ShipID": "404",
            "dataJSON": "ships/by-id/404/ship.json"
        },
        {
            "Name": "Birmingham",
            "ShipID": "405",
            "dataJSON": "ships/by-id/405/ship.json"
        },
        {
            "Name": "Aylwin",
            "ShipID": "406",
            "dataJSON": "ships/by-id/406/ship.json"
        },
        {
            "Name": "Bache",
            "ShipID": "407",
            "dataJSON": "ships/by-id/407/ship.json"
        },
        {
            "Name": "Black Prince",
            "ShipID": "408",
            "dataJSON": "ships/by-id/408/ship.json"
        },
        {
            "Name": "Stanly",
            "ShipID": "409",
            "dataJSON": "ships/by-id/409/ship.json"
        },
        {
            "Name": "Littorio",
            "ShipID": "410",
            "dataJSON": "ships/by-id/410/ship.json"
        },
        {
            "Name": "Conte di Cavour",
            "ShipID": "411",
            "dataJSON": "ships/by-id/411/ship.json"
        },
        {
            "Name": "Giulio Cesare",
            "ShipID": "412",
            "dataJSON": "ships/by-id/412/ship.json"
        },
        {
            "Name": "Zara",
            "ShipID": "413",
            "dataJSON": "ships/by-id/413/ship.json"
        },
        {
            "Name": "Trento",
            "ShipID": "414",
            "dataJSON": "ships/by-id/414/ship.json"
        },
        {
            "Name": "Carabiniere",
            "ShipID": "415",
            "dataJSON": "ships/by-id/415/ship.json"
        },
        {
            "Name": "U-110",
            "ShipID": "416",
            "dataJSON": "ships/by-id/416/ship.json"
        },
        {
            "Name": "Smalley",
            "ShipID": "417",
            "dataJSON": "ships/by-id/417/ship.json"
        },
        {
            "Name": "Gascogne \u00b5",
            "ShipID": "418",
            "dataJSON": "ships/by-id/418/ship.json"
        },
        {
            "Name": "Akagi \u00b5",
            "ShipID": "419",
            "dataJSON": "ships/by-id/419/ship.json"
        },
        {
            "Name": "Cleveland \u00b5",
            "ShipID": "420",
            "dataJSON": "ships/by-id/420/ship.json"
        },
        {
            "Name": "Sheffield \u00b5",
            "ShipID": "421",
            "dataJSON": "ships/by-id/421/ship.json"
        },
        {
            "Name": "Admiral Hipper \u00b5",
            "ShipID": "422",
            "dataJSON": "ships/by-id/422/ship.json"
        },
        {
            "Name": "Glasgow",
            "ShipID": "423",
            "dataJSON": "ships/by-id/423/ship.json"
        },
        {
            "Name": "Kasumi",
            "ShipID": "424",
            "dataJSON": "ships/by-id/424/ship.json"
        },
        {
            "Name": "Suruga",
            "ShipID": "425",
            "dataJSON": "ships/by-id/425/ship.json"
        },
        {
            "Name": "Ryuuhou",
            "ShipID": "426",
            "dataJSON": "ships/by-id/426/ship.json"
        },
        {
            "Name": "Halsey Powell",
            "ShipID": "427",
            "dataJSON": "ships/by-id/427/ship.json"
        },
        {
            "Name": "Biloxi",
            "ShipID": "428",
            "dataJSON": "ships/by-id/428/ship.json"
        },
        {
            "Name": "Uranami",
            "ShipID": "429",
            "dataJSON": "ships/by-id/429/ship.json"
        },
        {
            "Name": "Grozny",
            "ShipID": "431",
            "dataJSON": "ships/by-id/431/ship.json"
        },
        {
            "Name": "Minsk",
            "ShipID": "432",
            "dataJSON": "ships/by-id/432/ship.json"
        },
        {
            "Name": "Tashkent",
            "ShipID": "433",
            "dataJSON": "ships/by-id/433/ship.json"
        },
        {
            "Name": "Pamiat Merkuria",
            "ShipID": "434",
            "dataJSON": "ships/by-id/434/ship.json"
        },
        {
            "Name": "Chapayev",
            "ShipID": "436",
            "dataJSON": "ships/by-id/436/ship.json"
        },
        {
            "Name": "Gangut",
            "ShipID": "437",
            "dataJSON": "ships/by-id/437/ship.json"
        },
        {
            "Name": "Sovetskaya Rossiya",
            "ShipID": "441",
            "dataJSON": "ships/by-id/441/ship.json"
        },
        {
            "Name": "Intrepid",
            "ShipID": "442",
            "dataJSON": "ships/by-id/442/ship.json"
        },
        {
            "Name": "Bremerton",
            "ShipID": "443",
            "dataJSON": "ships/by-id/443/ship.json"
        },
        {
            "Name": "Cooper",
            "ShipID": "444",
            "dataJSON": "ships/by-id/444/ship.json"
        },
        {
            "Name": "Reno",
            "ShipID": "445",
            "dataJSON": "ships/by-id/445/ship.json"
        },
        {
            "Name": "Bluegill",
            "ShipID": "446",
            "dataJSON": "ships/by-id/446/ship.json"
        },
        {
            "Name": "Casablanca",
            "ShipID": "447",
            "dataJSON": "ships/by-id/447/ship.json"
        },
        {
            "Name": "Marblehead",
            "ShipID": "448",
            "dataJSON": "ships/by-id/448/ship.json"
        },
        {
            "Name": "Hanazuki",
            "ShipID": "449",
            "dataJSON": "ships/by-id/449/ship.json"
        },
        {
            "Name": "Naganami",
            "ShipID": "450",
            "dataJSON": "ships/by-id/450/ship.json"
        },
        {
            "Name": "Little Renown",
            "ShipID": "451",
            "dataJSON": "ships/by-id/451/ship.json"
        },
        {
            "Name": "Tartu",
            "ShipID": "452",
            "dataJSON": "ships/by-id/452/ship.json"
        },
        {
            "Name": "Richelieu",
            "ShipID": "453",
            "dataJSON": "ships/by-id/453/ship.json"
        },
        {
            "Name": "Jeanne d'Arc",
            "ShipID": "454",
            "dataJSON": "ships/by-id/454/ship.json"
        },
        {
            "Name": "Alg\u00e9rie",
            "ShipID": "455",
            "dataJSON": "ships/by-id/455/ship.json"
        },
        {
            "Name": "La Galissonni\u00e8re",
            "ShipID": "456",
            "dataJSON": "ships/by-id/456/ship.json"
        },
        {
            "Name": "Vauquelin",
            "ShipID": "457",
            "dataJSON": "ships/by-id/457/ship.json"
        },
        {
            "Name": "B\u00e9arn",
            "ShipID": "458",
            "dataJSON": "ships/by-id/458/ship.json"
        },
        {
            "Name": "Little Illustrious",
            "ShipID": "459",
            "dataJSON": "ships/by-id/459/ship.json"
        },
        {
            "Name": "Eskimo",
            "ShipID": "460",
            "dataJSON": "ships/by-id/460/ship.json"
        },
        {
            "Name": "Tone",
            "ShipID": "9001",
            "dataJSON": "ships/by-id/9001/ship.json"
        },
        {
            "Name": "Chikuma",
            "ShipID": "9002",
            "dataJSON": "ships/by-id/9002/ship.json"
        },
        {
            "Name": "Pola",
            "ShipID": "9006",
            "dataJSON": "ships/by-id/9006/ship.json"
        },
        {
            "Name": "Vittorio Veneto",
            "ShipID": "9007",
            "dataJSON": "ships/by-id/9007/ship.json"
        },
        {
            "Name": "Kirov",
            "ShipID": "9008",
            "dataJSON": "ships/by-id/9008/ship.json"
        },
        {
            "Name": "Sovetsky Soyuz",
            "ShipID": "9009",
            "dataJSON": "ships/by-id/9009/ship.json"
        }
    ]
}