{
    "AA120": "178",
    "AAInitial": "33",
    "AAKai": "0",
    "AAKai120": "0",
    "AAMax": "154",
    "ASW120": "212",
    "ASWInitial": "52",
    "ASWKai": "0",
    "ASWKai120": "0",
    "ASWMax": "192",
    "Acc120": "207",
    "AccInitial": "76",
    "AccKai": "0",
    "AccKai120": "0",
    "AccMax": "197",
    "Air120": "0",
    "AirInitial": "0",
    "AirKai": "0",
    "AirKai120": "0",
    "AirMax": "0",
    "Ammo120": "0",
    "AmmoInitial": "0",
    "AmmoKai": "0",
    "AmmoKai120": "0",
    "AmmoMax": "0",
    "Armor": "Light",
    "ArmorKai": "Light",
    "Artist": "Lino(\u756a\u8304)",
    "ArtistLink": "[http://weibo.com/p/1005051859846292 \u756a\u8304\u6559\u7236__Lino]",
    "ArtistPixiv": "[https://www.pixiv.net/member.php?id=238071 Lino@\u30ec\u30e0\u75c7\u672b\u671f]",
    "ArtistTwitter": "[https://twitter.com/lino__ Lino]",
    "CNName": "\u67e5\u5c14\u65af\u00b7\u5965\u65af\u672c",
    "Class": "Fletcher",
    "ConstructTime": "Drop Only",
    "Consumption120": "9",
    "ConsumptionInitial": "2",
    "ConsumptionKai": "0",
    "ConsumptionKai120": "0",
    "ConsumptionMax": "9",
    "Eq1BaseMax": "1",
    "Eq1EffInit": "115%",
    "Eq1EffInitMax": "125%",
    "Eq1Type": "DD Main Guns",
    "Eq2BaseMax": "2",
    "Eq2EffInit": "120%",
    "Eq2EffInitMax": "130%",
    "Eq2Type": "Torpedoes",
    "Eq3BaseMax": "1",
    "Eq3EffInit": "120%",
    "Eq3EffInitMax": "130%",
    "Eq3Type": "Anti-Air Guns",
    "Evade120": "158",
    "EvadeInitial": "59",
    "EvadeKai": "0",
    "EvadeKai120": "0",
    "EvadeMax": "154",
    "Fire120": "87",
    "FireInitial": "16",
    "FireKai": "0",
    "FireKai120": "0",
    "FireMax": "76",
    "Health120": "2112",
    "HealthInitial": "343",
    "HealthKai": "0",
    "HealthKai120": "0",
    "HealthMax": "1775",
    "JPName": "\u30c1\u30e3\u30fc\u30eb\u30ba\u30fb\u30aa\u30fc\u30b9\u30d0\u30fc\u30f3",
    "KRName": "\ucc30\uc2a4 \uc624\uc2a4\ubcf8",
    "Luck": "82",
    "Name": "Charles Ausburne",
    "Nationality": "Eagle Union",
    "Oxygen120": "0",
    "OxygenInitial": "0",
    "OxygenKai": "0",
    "OxygenKai120": "0",
    "OxygenMax": "0",
    "Rarity": "Elite",
    "Reload120": "215",
    "ReloadInitial": "79",
    "ReloadKai": "0",
    "ReloadKai120": "0",
    "ReloadMax": "187",
    "Remodel": "f",
    "ShipGroup": "Standard",
    "ShipID": "013",
    "Speed": "42",
    "SpeedKai": "0",
    "Torp120": "291",
    "TorpInitial": "54",
    "TorpKai": "0",
    "TorpKai120": "0",
    "TorpMax": "255",
    "Type": "Destroyer",
    "VA": "[https://twitter.com/m_satsuki_ Satsuki Morita]"
}